setup.py
scubboSetupToolsTestProject1/__init__.py
scubboSetupToolsTestProject1/testfile1.py
scubboSetupToolsTestProject1.egg-info/PKG-INFO
scubboSetupToolsTestProject1.egg-info/SOURCES.txt
scubboSetupToolsTestProject1.egg-info/dependency_links.txt
scubboSetupToolsTestProject1.egg-info/top_level.txt