Metadata-Version: 1.1
Name: scubboSetupToolsTestProject1
Version: 0.0.1
Summary: An initial test project to learn how PyPI works
Home-page: http://packages.python.org/scubboSetupToolsTestProject1
Author: Jack Jackson
Author-email: scubbojj@gmail.com
License: BSD
Keywords: example documentation tutorial
Platform: UNKNOWN
Classifier: Development Status :: 3 - Alpha
Classifier: Topic :: Utilities
Classifier: License :: OSI Approved :: BSD License
